README.md
setup.py
Tanki.egg-info/PKG-INFO
Tanki.egg-info/SOURCES.txt
Tanki.egg-info/dependency_links.txt
Tanki.egg-info/requires.txt
Tanki.egg-info/top_level.txt
tanki/__init__.py
tanki/drone.py
tanki/exceptions.py
tanki/grade_details.py
tanki/grades.py
tanki/hull.py
tanki/mode.py
tanki/module.py
tanki/paint.py
tanki/profile.py
tanki/rank.py
tanki/rating.py
tanki/supplies_usage.py
tanki/turret.py