Metadata-Version: 2.1
Name: Tanki
Version: 1.0.0
Summary: API wrapper for Tanki Online's ratings API
Home-page: https://github.com/wa1ker38552/tanki
Author: walker
Requires-Python: >=3.7
